testpakage/__init__.py
mtast-0.0.2.dist-info/LICENSE
mtast-0.0.2.dist-info/METADATA
mtast-0.0.2.dist-info/WHEEL
mtast-0.0.2.dist-info/top_level.txt
mtast-0.0.2.dist-info/RECORD
